pytest_junit_xray_xml/__init__.py
pytest_junit_xray_xml/_version.py
pytest_junit_xray_xml/exceptions.py
pytest_junit_xray_xml/fixtures.py
pytest_junit_xray_xml/junit_xml_xray_xml.py
pytest_junit_xray_xml/plugin.py
pytest_junit_xray_xml/utils.py
pytest_junit_xray_xml-0.2.0.dist-info/LICENSE
pytest_junit_xray_xml-0.2.0.dist-info/METADATA
pytest_junit_xray_xml-0.2.0.dist-info/WHEEL
pytest_junit_xray_xml-0.2.0.dist-info/entry_points.txt
pytest_junit_xray_xml-0.2.0.dist-info/top_level.txt
pytest_junit_xray_xml-0.2.0.dist-info/RECORD
